{
"code": 10000,
"message": "success",
"data": {
"changyanSid": "page\/5604992823",
"title": "\u8eab\u5f62\u66b4\u7626\u9762\u5bb9\u6194\u60b4\uff01S6\u5931\u5229\u540e\u5382\u957f\u7ec8\u9732\u9762",
"excerpt": "\u4e00\u64b8\u64b8\u4e00\u5929\uff0c\u5355\u624b\u80fd\u9006\u5929\uff0c\u59b9\u5b50\u653e\u4e00\u8fb9\uff0c\u57fa\u53cb\u56f4\u4e00\u5708\u3002Hi\uff0c\u5927\u5bb6\u597d\uff0c\u6b22\u8fce\u6765\u5230\u201c\u7adf\u62a5\u201d\u680f\u76ee\u65f6\u95f4\uff0c\u6bcf\u5929\u4e0e\u89c2\u4f17\u8001\u7237\u4eec\u7545\u804a\u64b8\u5708\u70ed\u70b9\u4e8b\u4ef6\uff0c\u4e0d\u89c1\u4e0d\u6563\u54df\uff01",
"banner": "http:\/\/files.15w.com\/image\/2016\/0616\/14660491062190.jpg",
"thumbnail": "http:\/\/files.15w.com\/image\/2016\/1028\/14776496292143.jpg",
"shareUrl": "http:\/\/lol.15w.com\/pages\/jb78.html",
"author": "15W",
"avatar": "http:\/\/files.15w.com\/image\/2016\/0715\/14685538019569.png",
"source": "15W",
"introduction": "",
"content": "<style>.detailsCon h2,h1{font-weight:600;font-family:PingFangSC-Medium,sans-serif}.container,.container .wrap,.detailsTit,.leaderCon,h1{position:relative}.container,.detailsTit,.detailsTit .ti,.leaderCon,h1{overflow:hidden}.banner img,.container .left img,.indent img{max-width:100%}.banner{min-height:100%}.wrap{margin:0 auto;clear:both;width:100%}.container .left{width:auto;float:none}.details{background-color:#fff}h1{color:#333;padding:1.5rem 2.25rem 0;font-size:1.25rem;text-align:center;line-height:1.2}.leaderCon{padding:0 .75rem;margin-top:.5rem;color:#666;font-size:.85rem;border-left:4px solid #dadada;margin-left:.75rem;text-indent:1.5em;text-align:justify}.indent .pic,.pic p{text-align:center}.detailsCon h2{margin-top:1.5rem;font-size:1rem;color:#333;margin-bottom:1.25rem}.detailsTit{padding:1rem .75rem .75rem;display:flex;justify-content:center;align-items:center;flex-direction:column}.detailsTit .pic{width:2rem;height:2rem;border:1px solid #b5b5b5;border-radius:50%;margin-bottom:.5rem;float:left}.detailsTit .ti{line-height:1.1rem;padding:0 0 .25rem .25rem;font-size:.9rem;color:#999}.detailsTit .art-time i{width:13px;height:13px;margin-top:4px;vertical-align:top;margin-right:5px;background:url(http:\/\/www.15w.com\/ui\/www\/v1\/img\/ui.png) -61px -47px no-repeat;display:inline-block}.art-time{color:#999}.leaderCon :before{content:\"\u201c\";color:#666;font-size:1.8rem;position:absolute;left:-1rem;top:-.3rem!important}.detailsCon,h2{position:relative;overflow:hidden}.themeBlue .leaderCon span{background:#0c82fb}.detailsCon p{padding:0 .75rem}h2{color:#212020;font-weight:400}.container{background:#fff}.detailsTit .pic img{-webkit-border-radius:50%;border-radius:50%}.detailsTit p span{margin-right:.5rem;font-size:.85rem}.indent p.cimg-desc{text-align:center;color:#999;padding-bottom:1.25rem;margin-top:-.5rem;font-size:.75rem}.container .left .detailsTit p{margin-top:0;overflow:hidden;padding-left:.25rem;padding-top:.25rem}.indent .pic{margin:1.5rem 0}.flat-content p img:nth-child(10),.flat-content p img:nth-child(11),.flat-content p img:nth-child(12),.flat-content p img:nth-child(2),.flat-content p img:nth-child(3),.flat-content p img:nth-child(4),.flat-content p img:nth-child(5),.flat-content p img:nth-child(6),.flat-content p img:nth-child(7),.flat-content p img:nth-child(8),.flat-content p img:nth-child(9),.indent .pic img:nth-child(2),.indent .pic img:nth-child(3),.indent .pic img:nth-child(4),.indent .pic img:nth-child(5){padding-top:1rem}.detailsCon h2 i{display:inline-block;margin-right:.5rem;width:.15rem}.container .left p{line-height:1.3rem;margin-top:.8rem;color:#333;font-size:.85rem;text-align:justify}iframe{width:100%}<\/style><div class=\"leaderCon\"><span>\u5f15\u8a00<\/span>Hi\uff0c\u5927\u5bb6\u597d\uff0c\u6b22\u8fce\u6765\u5230\u201c\u7adf\u62a5\u201d\u680f\u76ee\u65f6\u95f4\u3002\u6bcf\u665a\u4e5d\u70b9\uff0c\u6700\u70ed\u7684\u64b8\u5708\u8d44\u8baf\u5c3d\u5728\u638c\u63e1\uff01<\/div><div class=\"detailsCon\"><h2><i><\/i>\u6e38\u620f<\/h2><p><strong>\u6234\u4e0a\u5b83\u4e0d\u7528\u770b\u5c0f\u5730\u56fe\uff01\u9ed1\u79d1\u6280\u9879\u94fe\u53d6\u4ee3\u89c6\u91ce\uff1f<\/strong> <\/p><p>\u8fd1\u65e5\uff0c\u4e00\u6b3e\u53ef\u7a7f\u6234\u7684\u6e38\u620f\u914d\u4ef6\u4ea7\u54c1\u201cArc\u201d\u706b\u4e86\uff0c\u56e0\u4e3a\u4f69\u6234\u4e0a\u5b83\u4ee5\u540e\uff0c\u518d\u4e5f\u4e0d\u7528\u62c5\u5fc3\u73a9LOL\u7684\u65f6\u5019\u88ab\u4ebaGANK\u4e86\uff01\u56e0\u4e3a\u5b83\u53ef\u4ee5\u4e3a\u73a9\u5bb6\u63d0\u4f9b\u201c\u7b2c\u516d\u611f\u201d\u3002<\/p><p>\u5728\u6253LOL\u65f6\uff0c\u660e\u660e\u4e00\u4e9b\u773c\u770b\u5230\u654c\u4eba\u6b63\u5728\u5f80\u961f\u53cb\u7684\u65b9\u5411\u8d76\u8fc7\u53bb\uff0c\u4f46\u662f\u4ed6\u4eec\u5374\u4f9d\u7136\u4e0d\u8d70\u3002\u8fd9\u79cd\u60c5\u51b5\u4e00\u822c\u6709\u4e24\u4e2a\u539f\u56e0\uff1a\u4e00\u5c31\u662f\u89c9\u5f97\u81ea\u5df1\u6709\u95ea\u73b0\uff0c\u6765\u4e86\u4e5f\u80fd\u95ea\u73b0\u8dd1\u3002\u7b2c\u4e8c\u79cd\u5c31\u662f\u5fd9\u4e8e\u5bf9\u7ebf\uff0c\u6ca1\u529e\u6cd5\u5206\u5fc3\u770b\u5230\u5c0f\u5730\u56fe\u4e0a\u7684\u7ea2\u70b9\u3002\u9762\u5bf9\u8fd9\u4e9b\u60c5\u51b5\uff0c\u6211\u4eec\u8fd8\u662f\u53ef\u4ee5\u518d\u62a2\u6551\u4e00\u4e0b\u7684\uff01<\/p><p>\u897f\u96c5\u56fe\u4e00\u5bb6\u516c\u53f8\u516c\u5e03\u4e86\u4e00\u6b3e\u540d\u4e3a\u201cArc\u201d\u7684\u7279\u522b\u9879\u94fe\uff0c\u76ee\u6807\u662f\u4e3a\u73a9\u5bb6\u63d0\u4f9b\u201c\u7b2c\u4e09\u53ea\u773c\u775b\u201d\u3002\u8fd9\u4e2a\u9879\u94fe\u76f4\u63a5\u4e0e\u667a\u80fd\u624b\u673a\u914d\u5bf9\uff0c\u7528\u624b\u673a\u6444\u50cf\u5934\u8bfb\u53d6\u6e38\u620f\u5c0f\u5730\u56fe\uff0c\u4e0d\u6d89\u53ca\u5230\u6539\u4ee3\u7801\uff0c\u53d1\u73b0\u5f02\u5e38\u73af\u5883\u540e\u9879\u94fe\u4f1a\u53d1\u51fa\u9707\u52a8\u63d0\u9192\u73a9\u5bb6\u3002<\/p><p class=\"cimg\" align=\"center\"><img src=\"http:\/\/files.15w.com\/image\/2016\/1028\/14776210939838.jpg\" alt=\"\" \/> <\/p><p>\u5f53\u654c\u4eba\u8fdb\u5165\u89c6\u91ce\u8303\u56f4\u5185\uff0c\u9879\u94fe\u5c31\u4f1a\u6839\u636e\u4f4d\u7f6e\u6765\u9707\u52a8\uff0c\u654c\u4eba\u5728\u5de6\u8fb9\uff0c\u5b83\u7684\u5de6\u8fb9\u5c31\u4f1a\u9707\u52a8\uff0c\u51fa\u73b0\u5728\u53f3\u8fb9\uff0c\u53f3\u8fb9\u7684\u4e00\u5757\u4f4d\u7f6e\u5c31\u4f1a\u9707\u52a8\u3002\u632f\u52a8\u7684\u5f3a\u5ea6\u3001\u9891\u7387\u3001\u91cd\u590d\u90fd\u53ef\u4ee5\u8c03\u6574\uff0c\u4f7f\u5f97\u73a9\u5bb6\u4eec\u53ef\u4ee5\u4e0d\u7528\u65f6\u5e38\u5206\u5fc3\u5c0f\u5730\u56fe\u3002<\/p><p class=\"cimg\" align=\"center\"><img src=\"http:\/\/files.15w.com\/image\/2016\/1028\/14776210938285.jpg\" alt=\"\" \/> <\/p><p>\u201cArc\u201d\u652f\u6301\u5f53\u524d\u5f88\u591a\u7684\u70ed\u95e8\u6e38\u620f\uff0c\u6bd4\u5982\u300aCS\uff1aGO\u300b\u548c\u300a\u82f1\u96c4\u8054\u76df\u300b\u3002\u76ee\u524d\u8be5\u4ea7\u54c1\u6b63\u5728\u4f17\u7b79\u4e4b\u4e2d\uff0c\u76ee\u6807\u4e3a7.5\u4e07\u7f8e\u5143\u3002\u6839\u636e\u5b98\u65b9\u7684\u4ecb\u7ecd\uff0c\u6b63\u5728\u52a0\u5165\u66f4\u591a\u7684\u6e38\u620f\u652f\u6301\uff0c\u6bd4\u5982\u300aDota2\u300b\u3001\u300a\u5766\u514b\u4e16\u754c\u300b\u3001\u300a\u6218\u5730\u300b\u7b49\u3002<\/p><p class=\"cimg\" align=\"center\"><img src=\"http:\/\/files.15w.com\/image\/2016\/1028\/14776210939645.jpg\" alt=\"\" \/> <\/p><p>\u4e0d\u96be\u9884\u89c1\u7684\u662f\uff0c\u6bd4\u8d5b\u4e2d\u662f\u6ca1\u6cd5\u7528\u7684\uff0c\u4e0d\u8fc7\uff0c\u5728\u5e73\u65f6\u4e0a\u5206\u7684\u8fc7\u7a0b\u4e2d\uff0c\u5e94\u8be5\u8fd8\u662f\u4f1a\u6709\u4e0d\u5c11\u73a9\u5bb6\u9700\u8981\u5b83\u3002<\/p><p>\u76ee\u524d\u8fd9\u6b3e\u9879\u94fe\u4e5f\u6709\u4e00\u5b9a\u7684\u4e89\u8bae\uff0c\u90a3\u5c31\u662f\u8fd9\u79cd\u8f85\u52a9\u9879\u94fe\u7b97\u4e0d\u7b97\u5916\u6302\uff1f\u6211\u5e26\u4e86\u522b\u4eba\u6ca1\u5e26\u662f\u4e0d\u662f\u6709\u8fdd\u7535\u5b50\u7ade\u6280\u7684\u516c\u5e73\u539f\u5219\uff1f\u4e0d\u77e5\u9053\u5982\u679c\u8fd9\u6b3e\u9879\u94fe\u771f\u7684\u63a8\u51fa\uff0c\u5404\u4f4d\u4f1a\u4e70\u5417\uff1f<\/p><p class=\"cimg\" align=\"center\" style=\"text-align:left;\"><strong><span style=\"color:#E53333;\">\u8bbe\u8ba1\u5e08Meddler\uff1a\u6216\u589e\u52a0\u5230\u5341\u4e2aBAN\u4f4d\uff01<\/span><\/strong><strong><span style=\"color:#E53333;\"><\/span><\/strong> <\/p><p>\u4eca\u5929\u6709\u4e00\u4ef6\u8d85\u7ea7\u91cd\u5927\u7684\u4e8b\u60c5\u8981\u5ba3\u5e03\uff0c\u6211\u4eec\u4e4b\u524d\u8c08\u8fc7\u7684\u672a\u6765\u7684\u82f1\u96c4\u8054\u76dfBAN\u4f4d\u53ef\u80fd\u8981\u6269\u5927\u523010\u4e2a\uff01\u4eca\u5929\u62f3\u5934\u6e38\u620f\u8d1f\u8d23\u4ebaMeddler\u5728\u7f8e\u670d\u7684\u8bba\u575b\u4e0a\u56de\u5e16\u8c08\u5230\u4e86\u589e\u52a0BAN\u4f4d\u7684\u95ee\u9898\u3002<\/p><p>\u65b0\u7248\u5ba2\u6237\u7aef\u51fa\u6765\u4e4b\u540e\uff0c\u6211\u4eec\u8ba1\u5212\u66f4\u6df1\u5165\u7814\u7a7610\u4e2aBAN\u4f4d\u7684\u95ee\u9898\uff08\u82f1\u96c4\u8054\u76df\u9009\u62e9\u754c\u9762\u6539\u52a8\u4f1a\u5728\u65b0\u7248\u5ba2\u6237\u7aef\u4e0a\u9762\u5b9e\u65bd\uff0c\u800c\u4e0d\u662f\u65e7\u7248\u7684\u5ba2\u6237\u7aef\uff09\u3002\u6211\u4eec\u89c9\u5f97\u6211\u4eec\u5f88\u6709\u53ef\u80fd\u5e94\u752810\u4e2aBAN\u4f4d\uff0c\u4f46\u662f\u73b0\u5728\u8fd8\u662f\u4e0d\u80fd\u505a\u51fa\u4fdd\u8bc1\u3002\u5047\u8bbe\u6211\u4eec\u786e\u5b9e\u6253\u7b97\u505a10\u4e2aBAN\u4f4d\uff0c\u90a3\u4e48\u804c\u4e1a\u6bd4\u8d5b\u548c\u6b63\u5e38\u6e38\u620f\u4e2d\u7684\u6539\u53d8\u53ef\u80fd\u4f1a\u5206\u5f00\u6765\u5b9e\u65bd\u3002\uff08\u5f81\u53ec\u5339\u914d\u8ddf\u804c\u4e1a\u6bd4\u8d5b\u4e2d\u7684\u8d5b\u4e8b\u5f81\u53ec\u81ea\u5b9a\u4e49\u6a21\u5f0f\u6709\u4e0d\u540c\u7684\u7981\u9009\u6d41\u7a0b\uff09\u3002<\/p><p>\u6216\u8bb8\u589e\u52a0BAN\u4f4d\u7684\u8fd9\u4e00\u5929\u771f\u7684\u8981\u5230\u6765\u4e86\uff01<span style=\"line-height:1.5;\">\u540c\u65f6\u6709\u5916\u56fd\u7684\u73a9\u5bb6\u63d0\u51fa\u4e86\u4e00\u70b9\u95ee\u9898\uff1a<\/span> <\/p><p class=\"cimg\" align=\"center\"><img src=\"http:\/\/files.15w.com\/image\/2016\/1028\/14776264739478.jpg\" alt=\"\" \/> <\/p><p>\u4f60\u660e\u767d\uff0c\u5982\u679c\u4e00\u4e2a\u961f\u7981\u6b625\u4e2a\u51a0\u519b\u540c\u65f6\uff0c\u4e8c\u961f\u6709\u4e00\u4e2a\u5de8\u5927\u7684\u4f18\u52bf\uff0c\u56e0\u4e3a\u5728\u654c\u4eba\u5df2\u7ecf\u7981\u6b62\u4ed6\u4eec\u53ef\u4ee5\u7981\u6b62\u3002 \uff08\u6307\u793a\u9009\u62e9\u548c\u53ef\u80fd\u7981\u6b62\u7684\u4e1c\u897f\u7b2c\u4e8c\u961f\u60f3\u7981\u6b62\uff09\uff1f<\/p><p>\u4e3a\u6b64\u6e38\u620f\u8d1f\u8d23\u4eba\u4e5f\u5bf9\u6b64\u4f5c\u51fa\u4e86\u56de\u5e94\uff1a<\/p><p class=\"cimg\" align=\"center\"><img src=\"http:\/\/files.15w.com\/image\/2016\/1028\/14776266094796.png\" alt=\"\" \/> <\/p><p>\u6211\u4eec\u8c08\u5230\u7684\u7c7b\u4f3c\u7684\u53d8\u5316\u662f\u540c\u65f6\u7981\u6b62\u6240\u670910\u4e2a\u73a9\u5bb6\u3002 \u4f60\u770b\u5230\u4f60\u7684\u56e2\u961f\u7981\u6b62\/\u7981\u6b62\uff0c\u4f46\u4e0d\u662f\u654c\u4eba\u7981\u6b62\u3002 \u5931\u53bb\u80fd\u529b\u5851\u9020\u4f60\u7684\u7981\u4ee4\u54cd\u5e94\u654c\u4eba\uff0c\u4f46\u53ef\u80fd\u8282\u7701\u4e86\u5f88\u591a\u65f6\u95f4\u3002<\/p><div class=\"detailsCon\"><h2><i><\/i>\u8d5b\u4e8b<\/h2><p><strong><span style=\"color:#E53333;\">\u5382\u957fS6\u5931\u5229\u540e\u9996\u6b21\u9732\u9762 \u8138\u5e9e\u6d88\u7626\u60f9\u4eba\u5fc3\u75bc<\/span><\/strong> <\/p><p>\u90a3\u4e2a150\u65a4\u7684\u87b3\u8782\u6253\u91ce\u53c8\u56de\u6765\u4e86\uff0c\u7231\u4e4b\u6df1\uff0c\u8d23\u4e4b\u5207\u3002S6\u603b\u51b3\u8d5bLPL\u90fd\u9057\u61be\u843d\u8d25\u4e86\uff0c\u5708\u5185\u4e5f\u5f00\u59cb\u5bf9\u67d0\u4e9b\u9009\u624b\u7684\u4e00\u4e9b\u51b7\u5632\u70ed\u8bbd\uff0c\u5728\u4f17\u591a\u89c2\u4f17\u7684\u53e3\u4e2d\u8a00\u8bba\u6700\u591a\u7684\u65e0\u975e\u662fEDG\u7684\u5382\u957f\u3002\u5f88\u591a\u4eba\u90fd\u5728\u8bc4\u8bba\u5382\u957f\u83dc\u3001\u6df7\u5b50\uff0c\u90a3\u4e48\u6211\u5f88\u60f3\u95ee\u5927\u5bb6\u4e00\u4e2a\u95ee\u9898\uff0c\u5982\u679c\u4f60\u8eab\u4e3a\u4e00\u4e2a\u804c\u4e1a\u9009\u624b\uff0c\u4f60\u52aa\u529b\u4e86\u51e0\u5e74\u6253\u4e0a\u4e86\u4e16\u754c\u8d5b\uff0c\u4f46\u662f\u56e0\u70ba\u4f60\u7684\u8868\u73b0\u4e0d\u4f73\u800c\u5bfc\u81f4\u4e86\u6bd4\u8d5b\u5931\u8d25\uff0c\u56e0\u6b64\u88ab\u4eba\u8bf4\u4f60\u662f\u201c\u6df7\u5b50\u201d\u3002\u4f60\u540c\u610f\u4e48\uff1f<\/p><p>\u5382\u957f\u5728\u8fd9\u6b21S6\u4e16\u754c\u4e0a\u9762\u5931\u5229\u4e4b\u540e\u8fd1\u65e5\u4ed6\u7b2c\u4e00\u6b21\u9732\u9762\uff0c\u5382\u957f\u6b62\u6b65\u516b\u5f3a\u4e4b\u540e\u97e9\u670d\u4e5f\u4e0d\u4e0aRank\uff0c\u4e5f\u4e0d\u76f4\u64ad\uff0c\u800c\u56fd\u5185\u7684\u5404\u5927\u8d34\u5427\u5374\u662f\u8206\u8bba\u4e00\u8fb9\u5012\uff0c\u770b\u5b8c\u4e0b\u9762\u8fd9\u5f20\u56fe\u6211\u771f\u7684\u5fc3\u75bc\u5382\u957f\u4e86\u3002\u9996\u6b21\u9732\u9762\u5c31\u7626\u4e86\u4e00\u5927\u5708\uff0c\u76f8\u4fe1\u5382\u957f\u7684\u7c89\u4e1d\u4eec\u5e94\u8be5\u662f\u5f88\u5fc3\u75bc\u3002<\/p><p class=\"cimg\" align=\"center\"><img src=\"http:\/\/files.15w.com\/image\/2016\/1028\/14776416761158.jpg\" alt=\"\" \/> <\/p><p>\u74dc\u76ae\u5934\u8fd8\u662f\u90a3\u4e2a\u74dc\u76ae\u5934\uff0c\u5382\u957f\u8fd8\u662f\u90a3\u4e2a\u5382\u957f\u3002\u8138\u4e0a\u5f88\u660e\u663e\u7684\u7626\u4e86\u5f88\u591a\uff0c\u540c\u65f6\u4e5f\u6709\u5f88\u591a\u4eba\u90fd\u60f3\u8ba9\u5382\u957f\u56de\u6765\u76f4\u64ad\uff0c\u7ee7\u7eed\u5728\u76f4\u64ad\u4e0a\u9762\u8bf4\u4e00\u4e9b\u9a9a\u8bdd\u3002<\/p><p class=\"cimg\" align=\"center\"><img src=\"http:\/\/files.15w.com\/image\/2016\/1028\/14776418096563.jpg\" alt=\"\" \/> <\/p><p>\u6700\u540e\u7684\u6700\u540e\uff0c\u4f60\u7684\u7c89\u4e1d\u9700\u8981\u4f60\uff0c\u6b22\u8fce\u4f60\u56de\u6765\uff01\u4e5f\u8bf7\u4f60\u4e00\u5b9a\u8981\u7ee7\u7eed\u81ea\u5df1\u7684\u804c\u4e1a\u68a6\u60f3\uff0c\u4e0d\u8981\u5728\u610f\u5916\u754c\u7684\u8206\u8bba\uff0c\u7f51\u7edc\u8a00\u8bba\u5f80\u5f80\u662f\u6700\u4f24\u4eba\u7684\u3002\u61c2\u4f60\u7684\u4eba\u81ea\u7136\u61c2\u4f60\uff0c\u7c89\u4e1d\u4eec\u5e0c\u671b\u4f60\u80fd\u7ee7\u7eed\u505a\u4e00\u4e2a\u80fd\u5403\u80fd\u559d\u7684\u5382\u5b50\uff01<\/p><p><strong><span style=\"color:#E53333;\">\u9999\u9505\u7206\u6599\u4e09\u5e74\u5165\u767e\u4e07 \u7c89\u4e1d\u70ed\u8bae\u6211\u4eec\u4e5f\u5c31\u60f3\u60f3<\/span><\/strong> <\/p><p>\u6709\u7684\u65f6\u5019\u5982\u679c\u4e00\u4e2a\u4eba\u5f88\u803f\u76f4\u7684\u8bdd\uff0c\u5fc3\u91cc\u662f\u85cf\u4e0d\u4f4f\u79d8\u5bc6\u7684\uff0c\u4e0d\u7ba1\u662f\u522b\u4eba\u7684\u8fd8\u662f\u81ea\u5df1\u7684\u603b\u4f1a\u4e0d\u7ecf\u610f\u95f4\u6cc4\u9732\u51fa\u6765\u3002\u5c31\u5728\u8fd1\u65e5\uff0c\u9999\u9505\u5728\u76f4\u64ad\u4e4b\u4e2d\u5766\u8a00\u81ea\u5df1\u6253\u804c\u4e1a\u6253\u4e86\u4e09\u5e74\u624d\u8d5a\u4e86100\u4e07\u3002<\/p><p>\u9999\u9505\u7684\u8fd9\u4e2a\u201c\u624d\u201d\u5b57\u8ba9\u5f88\u591a\u4eba\u90fd\u611f\u53f9\u4e0d\u5df2\uff0c\u8fd9\u53ef\u80fd\u662f\u5f88\u591a\u4eba\u4e00\u8f88\u5b50\u90fd\u8d5a\u4e0d\u5230\u7684\u94b1\u3002\u4e5f\u6709\u4eba\u8bf4\uff0c\u65e2\u7136\u8fd9\u4e48\u8d5a\u94b1\u4e3a\u4ec0\u4e48\u6ca1\u6709\u4eba\u53bb\u6253\u804c\u4e1a\u5462\uff1f\u4e0d\u8fc7\u4e5f\u4e0d\u4e4f\u6709\u4eba\u8bf4\uff0c\u65e2\u7136\u90fd\u6709100\u4e07\u4e86\uff0c\u96be\u9053\u8fd8\u4e0d\u6ee1\u8db3\u5417\uff1f<\/p><p>\u4e0d\u8fc7\u6211\u4eec\u4ed4\u7ec6\u60f3\u60f3\uff0c\u9999\u9505\u8bf4\u4e09\u5e74\u624d100\u4e07\u8fd9\u53e5\u8bdd\u5176\u5b9e\u6ca1\u6bdb\u75c5\uff0c\u76f8\u6bd4\u90a3\u4e9b\u9000\u5f79\u5f00\u76f4\u64ad\u7684\u9009\u624b\uff0c\u6708\u5165\u767e\u4e07\u5e74\u85aa\u5343\u4e07\uff0c\u5728\u52a0\u4e0a\u5404\u79cd\u7b7e\u5b57\u8d39\u4e03\u4e03\u516b\u516b\u7684\uff0c\u5bf9\u4e8e\u9999\u9505\u7684\u4e00\u767e\u4e07\u6765\u8bf4\u786e\u5b9e\u4e0d\u503c\u4e00\u63d0\u3002<\/p><p class=\"cimg\" align=\"center\"><img src=\"http:\/\/files.15w.com\/image\/2016\/1028\/14776453595363.jpg\" alt=\"\" \/> <\/p><p>\u52aa\u529b\u6253\u6bd4\u8d5b\u4e09\u5e74\u624d\u767e\u4e07\uff0c\u804c\u4e1a\u9009\u624b\u52aa\u529b\u90a3\u4e48\u4e45\u8fd8\u4e0d\u5982\u4e00\u4e2a\u9000\u5f79\u9009\u624b\u76f4\u64ad\u4e00\u4e2a\u6708\u8d5a\u94b1\uff0c\u52bf\u5fc5\u4f1a\u6709\u5f88\u591a\u4eba\u5fc3\u91cc\u4e0d\u5e73\u8861\u3002\u6bcf\u5929\u52aa\u529b\u8bad\u7ec3\u8fd8\u8981\u88ab\u5404\u79cd\u89c4\u5219\u7ea6\u675f\uff0c\u94b1\u6323\u5f97\u5c11\u8fd8\u53ef\u80fd\u4f1a\u80cc\u9505\uff01\u4f46\u662f\u770b\u770b\u5404\u4f4d\u4e3b\u64ad\u4eec\u5404\u79cd\u5149\u9c9c\u4eae\u4e3d\uff0c\u8d5a\u7684\u76c6\u6ee1\u94b5\u6ee1\u3002\u90a3\u4e48\u6211\u4e3a\u4ec0\u4e48\u4e0d\u627e\u4e2a\u673a\u4f1a\u9000\u5f79\u76f4\u64ad\u5f00\u5e97\u5462\uff1f<\/p><p>\u6240\u4ee5\uff0c\u4ece\u8fd9\u4e2a\u89d2\u5ea6\u53bb\u8003\u8651\u5176\u5b9e\u9999\u9505\u7684\u8fd9\u756a\u8bdd\u4e5f\u5e76\u4e0d\u8fc7\u5206\u3002\u4e4b\u524d\u5c31\u6709\u65b0\u95fb\u66fe\u7ecf\u63d0\u5230\u8fc7\uff0c\u4e00\u4e9b\u4e3b\u64ad\u6216\u8005\u662f\u9000\u5f79\u9009\u624b\u8eab\u4ef7\u5343\u4e07\uff0c\u800c\u4e14\u8de8\u8db3\u5f71\u89c6\u3001\u6b4c\u66f2\u548c\u6e38\u620f\uff0c\u5c5e\u4e8e\u5168\u80fd\u7684\u4e09\u6816\u660e\u661f\u3002<\/p><p>\u5f53\u521d\u6700\u70ed\u95e8\u7684\u83ab\u8fc7\u4e8e\u5916\u754c\u75af\u4f20MISS\u5f53\u65f6\u63a5\u53d7\u300a\u5f00\u5fc3\u76f4\u64ad\u300b\u680f\u76ee\u65f6\u7206\u51fa\u76841700\u4e07\u5408\u7ea6\uff0c\u5f53\u65f6\u8fdeMiss\u81ea\u5df1\u90fd\u88ab\u8fd9\u4e2a\u6d88\u606f\u5413\u5230\uff0c\u89c9\u5f97\u6709\u4e9b\u4e0d\u53ef\u601d\u8bae\u3002<\/p><p class=\"cimg\" align=\"center\"><img src=\"http:\/\/files.15w.com\/image\/2016\/1028\/147764810275469.jpg\" alt=\"\" \/> <\/p><p>\u4ece\u4e0a\u56fe\u4e2d\u6211\u4eec\u4e0d\u96be\u770b\u51fa\uff0c\u4e0d\u7ba1\u662f\u9000\u5f79\u9009\u624b\u4e94\u4e94\u5f00\u8fd8\u662f\u82e5\u98ce\u5e74\u85aa\u90fd\u8fc7\u5343\u4e07\uff0c\u76f8\u6bd4\u9999\u9505\u7684\u4e09\u5e74\u767e\u4e07\u6765\u8bf4\u786e\u5b9e\u66f4\u52a0\u5438\u5f15\u773c\u7403\u3002\u4f5c\u4e3a\u4e00\u4e2a\u804c\u4e1a\u9009\u624b\uff0c\u6bcf\u5929\u52aa\u529b\u8bad\u7ec3\u4e3a\u4e86\u6bd4\u8d5b\u505a\u5404\u79cd\u7684\u51c6\u5907\uff0c\u5230\u5934\u6765\u8fd8\u4e0d\u5982\u4e00\u4e2a\u5356\u8089\u677e\u997c\u6216\u8005\u662f\u62cdMV\u7684\u9000\u5f79\u9009\u624b\u6765\u7684\u5de5\u8d44\u9ad8\uff0c\u4f1a\u6709\u804c\u4e1a\u9009\u624b\u62b1\u6028\u4e5f\u662f\u4eba\u4e4b\u5e38\u60c5\u3002<\/p><p>\u5982\u4eca\uff0c\u5f88\u591a\u9009\u624b\u90fd\u4f1a\u840c\u751f\u51fa\u4e00\u79cd\u4e0d\u597d\u7684\u60f3\u6cd5\uff0c\u5c31\u662f\u522b\u4eba\u9000\u5f79\u5f00\u76f4\u64ad\u5c31\u80fd\u5e74\u5165\u5343\u4e07\uff0c\u81ea\u5df1\u4e3a\u4ec0\u4e48\u8fd8\u8981\u8fd9\u4e48\u52aa\u529b\u7684\u6253\u804c\u4e1a\uff0c\u968f\u4fbf\u6253\u4e24\u5e74\u7136\u540e\u9000\u5f79\u5356\u997c\u4e0d\u662f\u8fc7\u7684\u66f4\u52a0\u8212\u670d\u3002\u8fd9\u4e5f\u95f4\u63a5\u5bfc\u81f4\u5f88\u591a\u6709\u6f5c\u529b\u7684\u65b0\u4eba\u90fd\u9009\u62e9\u6253\u4e24\u5e74\u804c\u4e1a\u5c31\u9000\u5f79\uff0c\u4e5f\u5f71\u54cd\u5230\u56fd\u5185\u7684\u8054\u8d5b\u7684\u53d1\u5c55\uff0c\u5f88\u591a\u4eba\u90fd\u5931\u53bb\u4e86\u8fdb\u53d6\u5fc3\u3002<\/p><p>\u4e09\u5e74\u5165\u767e\u4e07\uff0c\u8bf4\u591a\u4e0d\u591a\uff0c\u8bf4\u5c11\u4e0d\u5c11\uff0c\u8981\u770b\u5728\u4ec0\u4e48\u4f4d\u7f6e\uff0c\u505a\u4ec0\u4e48\u4e8b\u60c5\u3002<\/p><div class=\"detailsCon\"><h2><i><\/i>\u5a31\u4e50<\/h2><p class=\"cimg\" align=\"center\" style=\"text-align:left;\"><strong><span style=\"color:#E53333;\">\u6212\u7f51\u4e13\u5bb6\u4e92\u76f8\u6495\u903c\uff1f\u9676\u5b8f\u5f00\u70ae\u8f70\u6768\u6c38\u4fe1<\/span><\/strong><strong><span style=\"color:#E53333;\"><\/span><\/strong> <\/p><p>\u201c\u7f51\u763e\u4e13\u5bb6\u201d\u9676\u5b8f\u5f00\u5fae\u535a\u53d1\u6587\u79f0\u8fd1\u5e74\u6765\u56fd\u5185\u7684\u5404\u79cd\u6212\u7f51\u673a\u6784\u6253\u7740\u5fc3\u91cc\u6cbb\u7597\u7684\u5e4c\u5b50\u5751\u5bb3\u4e86\u8bb8\u591a\u5bb6\u957f\u548c\u5b69\u5b50\uff0c\u5176\u77db\u5934\u76f4\u6307\u53e6\u4e00\u4f4d\u4ee5\u201c\u7535\u51fb\u7597\u6cd5\u201d\u95fb\u540d\u7684\u201c\u78c1\u7206\u6b65\u5175\u201d\u6768\u6c38\u4fe1\u3002<\/p><p>\u503c\u5f97\u4e00\u63d0\u7684\u662f\uff0c\u9676\u5b8f\u5f00\u66fe\u56e0\u79f0\u7f51\u7edc\u6e38\u620f\u4e3a\u201c\u6bd2\u54c1\u201d\u5f15\u53d1\u7fa4\u4f17\u6781\u5927\u53cd\u54cd\uff0c\u5728\u8bb8\u591a\u4eba\u5fc3\u4e2d\u4ed6\u4e5f\u4e0d\u662f\u4ec0\u4e48\u597d\u4e1c\u897f\uff0c\u6b64\u756a\u9676\u5b8f\u5f00\u516c\u5f00\u70ae\u8f70\u6768\u6c38\u4fe1\uff0c\u4ee4\u4e0d\u5c11\u7f51\u53cb\u4e0d\u7981\u8054\u60f3\uff0c\u9676\u5b8f\u5f00\u8fd9\u662f\u8981\u7ec8\u7ed3\u6768\u6c38\u4fe1\u5bf9\u4e8e\u201c\u6212\u7f51\u201d\u7684\u7edf\u6cbb\uff1f<\/p><p class=\"cimg\" align=\"center\"><img src=\"http:\/\/files.15w.com\/image\/2016\/1028\/14776223028285.jpg\" alt=\"\" \/> <\/p><p class=\"cimg\" align=\"center\"><img src=\"http:\/\/files.15w.com\/image\/2016\/1028\/147762217240293.png\" alt=\"1\" \/> <\/p><p>\u5bf9\u4e8e\u6212\u7f51\uff0c\u9676\u5b8f\u5f00\u8fd8\u63d0\u5230\uff0c\u4e0d\u8981\u6307\u8d23\u5b69\u5b50\u201c\u7f51\u763e\u201d\uff0c\u8981\u4ece\u4f60\u5b69\u5b50\u65e9\u671f\u6210\u957f\u8fc7\u7a0b\u4e2d\u627e\u95ee\u9898\u2014\u2014\u201c\u517b\u4e0d\u6559\uff0c\u7236\u4e4b\u8fc7\u201d\u4e2d\u7684\u201c\u8fc7\u201d\u662f\u4ec0\u4e48\uff0c\u662f\u4ec0\u4e48\u5bfc\u81f4\u4f60\u5b69\u5b50\u7684\u6027\u683c\u548c\u4eba\u683c\u51fa\u73b0\u79cd\u79cd\u95ee\u9898\uff0c\u627e\u5230\u5b69\u5b50\u8eab\u4e0a\u95ee\u9898\u4ea7\u751f\u7684\u6839\u6e90\u624d\u77e5\u9053\u5e94\u8be5\u4ece\u54ea\u513f\u89e3\u51b3\u8d77\u3002<\/p><p><strong>\u4eba\u7269\u4ecb\u7ecd \u9676\u5b8f\u5f00<\/strong> <\/p><p class=\"cimg\" align=\"center\"><img src=\"http:\/\/files.15w.com\/image\/2016\/1028\/1477621303418.jpg\" alt=\"\" \/> <\/p><p>2009\u5e747\u670817\u65e5\uff0c\u9676\u5b8f\u5f00\u5728\u7535\u89c6\u8282\u76ee\u4e2d\u629b\u51fa\u7f51\u7edc\u6e38\u620f\u662f\u201c\u6bd2\u54c1\u201d\u4e00\u8bf4\u540e\uff0c\u5373\u5f15\u8d77\u6781\u5927\u53cd\u54cd\uff0c\u968f\u540e\u4ed6\u4e0e\u7f51\u7edc\u6e38\u620f\u73a9\u5bb6\u5728\u7f51\u7edc\u4e0a\u201c\u820c\u8fa9\u201d\u4e09\u4e2a\u56de\u5408\u3002\u73a9\u5bb6\u5f3a\u70c8\u8981\u6c42\u9676\u5b8f\u5f00\u9053\u6b49\uff0c\u5bf9\u5176\u4e5f\u8fdb\u884c\u4e86\u65e0\u9650\u5347\u7ea7\u7684\u4eba\u8089\u641c\u7d22\uff0c\u5e76\u5bf9\u5176\u5b66\u672f\u80cc\u666f\u4e5f\u8fdb\u884c\u4e86\u4e00\u756a\u8d28\u7591\u3002\u4e00\u4e2a\u540d\u4e3a\u201c500\u4e07\u73a9\u5bb6\u8054\u5408\u7b7e\u540d\u5e16\u201d\u5728\u7f51\u7ad9\u6d41\u4f20\uff0c\u5f88\u591a\u73a9\u5bb6\u8981\u6c42\u9676\u5b8f\u5f00\u4e3a\u7f51\u7edc\u6e38\u620f\u201c\u6bd2\u54c1\u201d\u8bf4\u5411\u73a9\u5bb6\u9053\u6b49\u3002<\/p><p><strong>\u6768\u6c38\u4fe1<\/strong> <\/p><p class=\"cimg\" align=\"center\"><img src=\"http:\/\/files.15w.com\/image\/2016\/1028\/14776214439913.jpg\" alt=\"\" \/> <\/p><p>\u6768\u6c38\u4fe1\u662f\u4e34\u6c82\u5e02\u7b2c\u56db\u4eba\u6c11\u533b\u9662\u526f\u9662\u957f\uff0c\u4e34\u6c82\u5e02\u7f51\u7edc\u6210\u763e\u6212\u6cbb\u4e2d\u5fc3\uff08\u7b80\u79f0\u4e34\u6c82\u7f51\u6212\u4e2d\u5fc3\uff09\u4e3b\u4efb\uff0c\u88ab\u79f0\u4e3a\u201c\u5168\u56fd\u6212\u7f51\u763e\u4e13\u5bb6\u201d\u3002<\/p><p class=\"cimg\" align=\"center\"><img src=\"http:\/\/files.15w.com\/image\/2016\/1028\/14776218725785.jpg\" alt=\"\" \/> <\/p><p style=\"text-align:center;\"><strong>13\u53f7\u6cbb\u7597\u5ba4\u91cc\u7684\u7535\u51fb\u7597\u6cd5<\/strong> <\/p><p>\u5728\u6768\u6c38\u4fe1\u7684\u6212\u7f51\u4e2d\u5fc3\uff0c\u60e8\u65e0\u4eba\u9053\u7684\u6fc0\u8fdb\u201c\u7535\u51fb\u7597\u6cd5\u201d\uff0c\u7ed9\u65e0\u6570\u5b69\u5b50\u7559\u4e0b\u4e86\u65e0\u6cd5\u6d88\u9664\u7684\u5fc3\u7406\u521b\u4f24\uff0c\u5b69\u5b50\u4eec\u7a0d\u6709\u72af\u9519\u5c31\u8981\u906d\u53d7\u7535\u51fb\u6cbb\u7597\uff0c\u903c\u8feb\u5b69\u5b50\u5c48\u670d\u3002<\/p><p class=\"cimg\" align=\"center\"><strong> \u5634\u4e0a\u8bf4\u68a6\u60f3\u80cc\u540e\u7ea6\u70ae\uff1f\u7f51\u4f20\u524dLGD\u6253\u91ce\u5c0f\u7199\u8349\u7c89<\/strong> <\/p><p>\u8fd1\u65e5\u67d0\u5fae\u535a\u7f51\u53cb\u533f\u540d\u7206\u6599\u4e00\u5219LPL\u804c\u4e1a\u9009\u624b\u7684\u8349\u7c89\u4e11\u95fb\uff0c\u800c\u4e8b\u4ef6\u7684\u7126\u70b9\u5219\u662f\u524dLGD\u66ff\u8865\u6253\u91ceXiaoxi\uff0c\u636e\u7206\u6599\u4eba\u8bb2\u8ff0\uff0c<span>Xiaoxi\u5634\u91cc\u4e00\u76f4\u8bf4\u7740\u68a6\u60f3\uff0c\u80cc\u5730\u91cc\u5374\u628a\u624b\u4f38\u5411\u7c89\u4e1d\u7fa4\u4f53\u3002<\/span> <\/p><p class=\"cimg\" align=\"center\"><img src=\"http:\/\/files.15w.com\/image\/2016\/1028\/14776401663771.jpg\" alt=\"\" \/> <\/p><p class=\"cimg\" align=\"center\"><img src=\"http:\/\/files.15w.com\/image\/2016\/1028\/14776398583069.jpg\" alt=\"\" \/> <\/p><p class=\"cimg\" align=\"center\"><img src=\"http:\/\/files.15w.com\/image\/2016\/1028\/14776398585586.jpg\" alt=\"\" \/> <\/p><p><strong>\u968f\u540e\u7206\u6599\u8005\u8d34\u51fa\u6765\u4e86Xiaoxi\u4e0e\u4ed6\u7684\u597d\u670b\u53cb\u7684\u804a\u5929\u622a\u56fe\uff1a<\/strong> <\/p><p class=\"cimg\" align=\"center\"><img src=\"http:\/\/files.15w.com\/image\/2016\/1028\/14776398587194.jpg\" alt=\"\" \/> <\/p><p>\u968f\u540e\u8fd9\u540d\u7206\u6599\u8005\u4e5f\u76f4\u8a00LPL\u73b0\u5728\u5b58\u5728\u7684\u98ce\u6c14\u771f\u7684\u5f88\u6709\u95ee\u9898\u3002\u67d0\u4e9b\u804c\u4e1a\u961f\u5458\u53e3\u4e2d\u558a\u7740\u52aa\u529b\u8bad\u7ec3\uff0c\u8bf4\u4ec0\u4e48\u4e3a\u4e86\u68a6\u60f3\u6253\u804c\u4e1a\uff0c\u5374\u501f\u4e2a\u8fd9\u4e2a\u673a\u4f1a\u628a\u624b\u4f38\u5411\u4e86\u7c89\u4e1d\u7fa4\u4f53\u3002<\/p><p class=\"cimg\" align=\"center\"><img src=\"http:\/\/files.15w.com\/image\/2016\/1028\/14776398589354.jpg\" alt=\"\" \/> <\/p><p class=\"cimg\" align=\"center\"><img src=\"http:\/\/files.15w.com\/image\/2016\/1028\/14776398588655.jpg\" alt=\"\" \/> <\/p><p class=\"cimg\" align=\"center\"><img src=\"http:\/\/files.15w.com\/image\/2016\/1028\/14776398581509.jpg\" alt=\"\" \/> <\/p><p>\u90a3\u540d\u535a\u4e3b\u968f\u540e\u5728\u9694\u65e5\u51cc\u6668\u53c8\u8d34\u51fa\u6765\u4e00\u6bb5\u5bf9\u8bdd\u3002<\/p><p class=\"cimg\" align=\"center\"><img src=\"http:\/\/files.15w.com\/image\/2016\/1028\/14776398599463.jpg\" alt=\"\" \/> <\/p><p>\u4e8b\u4ef6\u8fdb\u5c55\u5230\u6b64\u8fd8\u6ca1\u4e00\u4e2a\u5b8c\u5168\u53ef\u4ee5\u4ee4\u4eba\u4fe1\u670d\u7684\u8bc1\u636e\uff0c<strong>\u800c\u5f53\u4e8b\u4ebaxiaoxi\u4e5f\u5728\u8fd9\u6761\u5fae\u535a\u7559\u8a00\uff1a<\/strong> <\/p><p class=\"cimg\" align=\"center\"><img src=\"http:\/\/files.15w.com\/image\/2016\/1028\/1477640991993.png\" alt=\"\" \/> <\/p><p class=\"cimg\" align=\"center\" style=\"text-align:left;\">\u6070\u597d\u8fd9\u4f1a\u8d76\u4e0aLPL\u5728S6\u603b\u51b3\u8d5b\u7684\u5931\u5229\uff0c\u5708\u5185\u5708\u5916\u7684\u4eba\u6b63\u5728\u53cd\u601d\u6211\u4eec\u5230\u5e95\u8f93\u5728\u4ec0\u4e48\u5730\u65b9\uff1f\u6709\u4eba\u8bf4\u4f53\u5236\uff1f\u6709\u4eba\u8bf4\u8bad\u7ec3\u7684\u6001\u5ea6\uff1f\u66f4\u6709\u4eba\u8bf4\u4ff1\u4e50\u90e8\u5bf9\u4e8e\u9009\u624b\u7684\u7ba1\u7406\u6709\u95ee\u9898\u3002\u6240\u4ee5\u8fd9\u4e2a\u4e8b\u4ef6\u4e00\u7ecf\u62ab\u9732\u8fc5\u901f\u5f15\u8d77\u4e86\u5404\u5927\u5a92\u4f53\u7684\u8f6c\u8f7d\u3002<\/p><p class=\"cimg\" align=\"center\" style=\"text-align:left;\"><strong>\u5f53\u4e8b<\/strong><strong>\u4ebaXiaoxi\u4e8e27\u65e5\u6b63\u5f0f<\/strong><strong>\u505a\u51fa\u56de\u5e94<\/strong><strong>\uff1a<\/strong> <\/p><p class=\"cimg\" align=\"center\"><img src=\"http:\/\/files.15w.com\/image\/2016\/1028\/14776411064720.png\" alt=\"\" \/> <\/p><p class=\"cimg\" align=\"center\" style=\"text-align:left;\">\u6b64\u4e8b\u81f3\u4eca\u5c1a\u672a\u88ab\u8bc1\u5b9e\uff0c\u5e0c\u671b\u89c2\u4f17\u8001\u7237\u4eec\u4ee5\u5e73\u5e38\u5fc3\u5bf9\u5f85\uff01<\/p><\/div><\/div><\/div><script> for(var a=document.documentElement.clientWidth,b,c,d,e=document.getElementsByTagName(\"iframe\"),f=document.getElementsByTagName(\"embed\"),g=0;g<e.length;g++)c=e[g].getAttribute(\"o_width\")?e[g].getAttribute(\"o_width\"):e[g].getAttribute(\"width\"),c=\"100%\"==c?980:c,d=e[g].getAttribute(\"o_height\")?e[g].getAttribute(\"o_height\"):e[g].getAttribute(\"height\"),a<c?(b=parseInt(a*d\/c),e[g].setAttribute(\"width\",\"100%\"),e[g].setAttribute(\"height\",b)):(e[g].setAttribute(\"width\",c),e[g].setAttribute(\"height\",d)),e[g].setAttribute(\"o_width\", c),e[g].setAttribute(\"o_height\",d);for(g=0;g<f.length;g++)c=f[g].getAttribute(\"o_width\")?f[g].getAttribute(\"o_width\"):f[g].getAttribute(\"width\"),c=\"100%\"==c?980:c,d=f[g].getAttribute(\"o_height\")?f[g].getAttribute(\"o_height\"):f[g].getAttribute(\"height\"),a<c?(b=parseInt(a*d\/c),f[g].setAttribute(\"width\",\"100%\"),f[g].setAttribute(\"height\",b)):(f[g].setAttribute(\"width\",c),f[g].setAttribute(\"height\",d)),f[g].setAttribute(\"o_width\",c),f[g].setAttribute(\"o_height\",d); <\/script>",
"pastlist": [{
"thumbnail": "http:\/\/files.15w.com\/image\/2016\/1027\/14775687925489.jpg",
"title": "\u5c0f\u72d7Tabe\u53cc\u6392 \u9047\u5371\u9669\u7b2c\u4e00\u53cd\u5e94\u558aMata\u6551\u6211",
"excerpt": "\u4e00\u64b8\u64b8\u4e00\u5929\uff0c\u5355\u624b\u80fd\u9006\u5929\uff0c\u59b9\u5b50\u653e\u4e00\u8fb9\uff0c\u57fa\u53cb\u56f4\u4e00\u5708\u3002Hi\uff0c\u5927\u5bb6\u597d\uff0c\u6b22\u8fce\u6765\u5230\u201c\u7adf\u62a5\u201d\u680f\u76ee\u65f6\u95f4\uff0c\u6bcf\u5929\u4e0e\u89c2\u4f17\u8001\u7237\u4eec\u7545\u804a\u64b8\u5708\u70ed\u70b9\u4e8b\u4ef6\uff0c\u4e0d\u89c1\u4e0d\u6563\u54df\uff01",
"tagName": "",
"tagColor": "",
"articleType": 9,
"extra": "5604992803"
}, {
"thumbnail": "http:\/\/files.15w.com\/image\/2016\/1027\/14775327389595.jpg",
"title": "Mata\u6216\u5f53\u6559\u7ec3\uff01EDG\u97e9\u63f4\u804a\u5929\u66dd\u5149\u56de\u97e9\uff1f",
"excerpt": "\u4e00\u64b8\u64b8\u4e00\u5929\uff0c\u5355\u624b\u80fd\u9006\u5929\uff0c\u59b9\u5b50\u653e\u4e00\u8fb9\uff0c\u57fa\u53cb\u56f4\u4e00\u5708\u3002Hi\uff0c\u5927\u5bb6\u597d\uff0c\u6b22\u8fce\u6765\u5230\u201c\u7adf\u62a5\u201d\u680f\u76ee\u65f6\u95f4\uff0c\u6bcf\u5929\u4e0e\u89c2\u4f17\u8001\u7237\u4eec\u7545\u804a\u64b8\u5708\u70ed\u70b9\u4e8b\u4ef6\uff0c\u4e0d\u89c1\u4e0d\u6563\u54df\uff01",
"tagName": "",
"tagColor": "",
"articleType": 9,
"extra": "5604992603"
}, {
"thumbnail": "http:\/\/files.15w.com\/image\/2016\/1026\/14774460909388.jpg",
"title": "\u5c0f\u72d7\u5973\u67aa\u8f85\u52a9\u906d\u75af\u72c2\u8fb1\u9a82 \u76f4\u8a00\u56fd\u670d\u8d28\u91cf\u592a\u5dee",
"excerpt": "\u4e00\u64b8\u64b8\u4e00\u5929\uff0c\u5355\u624b\u80fd\u9006\u5929\uff0c\u59b9\u5b50\u653e\u4e00\u8fb9\uff0c\u57fa\u53cb\u56f4\u4e00\u5708\u3002Hi\uff0c\u5927\u5bb6\u597d\uff0c\u6b22\u8fce\u6765\u5230\u201c\u7adf\u62a5\u201d\u680f\u76ee\u65f6\u95f4\uff0c\u6bcf\u5929\u4e0e\u89c2\u4f17\u8001\u7237\u4eec\u7545\u804a\u64b8\u5708\u70ed\u70b9\u4e8b\u4ef6\uff0c\u4e0d\u89c1\u4e0d\u6563\u54df\uff01",
"tagName": "",
"tagColor": "",
"articleType": 9,
"extra": "5604992563"
}, {
"thumbnail": "http:\/\/files.15w.com\/image\/2016\/1025\/14773586636587.jpg",
"title": "\u5927\u795e\u7528\u811a\u73a9\u76f2\u50e7\u8fd8R\u95ea\uff01\u5382\u957f4396\u778e\u60e8\u88ab\u9ed1",
"excerpt": "\u4e00\u64b8\u64b8\u4e00\u5929\uff0c\u5355\u624b\u80fd\u9006\u5929\uff0c\u59b9\u5b50\u653e\u4e00\u8fb9\uff0c\u57fa\u53cb\u56f4\u4e00\u5708\u3002Hi\uff0c\u5927\u5bb6\u597d\uff0c\u6b22\u8fce\u6765\u5230\u201c\u7adf\u62a5\u201d\u680f\u76ee\u65f6\u95f4\uff0c\u6bcf\u5929\u4e0e\u89c2\u4f17\u8001\u7237\u4eec\u7545\u804a\u64b8\u5708\u70ed\u70b9\u4e8b\u4ef6\uff0c\u4e0d\u89c1\u4e0d\u6563\u54df\uff01",
"tagName": "",
"tagColor": "",
"articleType": 9,
"extra": "5604992523"
}, {
"thumbnail": "http:\/\/files.15w.com\/image\/2016\/1021\/14770132265265.jpg",
"title": "EDG\u6559\u7ec3\u963f\u5e03\u53d1\u6587\u4e3b\u52a8\u63fd\u9505\uff01",
"excerpt": "\u4e00\u64b8\u64b8\u4e00\u5929\uff0c\u5355\u624b\u80fd\u9006\u5929\uff0c\u59b9\u5b50\u653e\u4e00\u8fb9\uff0c\u57fa\u53cb\u56f4\u4e00\u5708\u3002Hi\uff0c\u5927\u5bb6\u597d\uff0c\u6b22\u8fce\u6765\u5230\u201c\u7adf\u62a5\u201d\u680f\u76ee\u65f6\u95f4\uff0c\u6bcf\u5929\u4e0e\u89c2\u4f17\u8001\u7237\u4eec\u7545\u804a\u64b8\u5708\u70ed\u70b9\u4e8b\u4ef6\uff0c\u4e0d\u89c1\u4e0d\u6563\u54df\uff01",
"tagName": "",
"tagColor": "",
"articleType": 9,
"extra": "5604992443"
}]
}
}